libstored/__init__.py
libstored/exceptions.py
libstored/heatshrink.py
libstored/tk.py
libstored/version.py
libstored/asyncio/__init__.py
libstored/asyncio/csv.py
libstored/asyncio/event.py
libstored/asyncio/tk.py
libstored/asyncio/worker.py
libstored/asyncio/zmq.py
libstored/cli/__init__.py
libstored/cli/__main__.py
libstored/cmake/__init__.py
libstored/cmake/__main__.py
libstored/data/.clang-tidy
libstored/data/CMakeLists.txt.tmpl
libstored/data/LICENSES/CC0-1.0.txt
libstored/data/LICENSES/MIT.txt
libstored/data/LICENSES/MPL-2.0.txt
libstored/data/cmake/FindLibstored.cmake.tmpl
libstored/data/cmake/LibstoredStoresConfig.cmake.in
libstored/data/cmake/libstored.cmake
libstored/data/dist/common/FindHeatshrink.cmake
libstored/data/dist/common/FindTinyAES.cmake
libstored/data/dist/common/FindZeroMQ.cmake
libstored/data/dist/common/FindZth.cmake
libstored/data/doc/SHA1SUM.tmpl
libstored/data/doc/libstored-src.spdx.tmpl
libstored/data/doc/store.csv.tmpl
libstored/data/doc/store.py.tmpl
libstored/data/doc/store.rtf.tmpl
libstored/data/doc/store.yml.tmpl
libstored/data/fpga/rtl/pkg.vhd
libstored/data/fpga/rtl/protocol.vhd
libstored/data/fpga/rtl/store.vhd.tmpl
libstored/data/fpga/rtl/store_pkg.vhd.tmpl
libstored/data/fpga/rtl/util.vhd
libstored/data/fpga/rtl/variable.vhd
libstored/data/fpga/tb/tb_pkg.vhd
libstored/data/fpga/vivado/vivado.tcl.tmpl
libstored/data/include/stored
libstored/data/include/stored.h
libstored/data/include/stored_config.h
libstored/data/include/libstored/aes.h
libstored/data/include/libstored/allocator.h
libstored/data/include/libstored/components.h
libstored/data/include/libstored/compress.h
libstored/data/include/libstored/config.h
libstored/data/include/libstored/debugger.h
libstored/data/include/libstored/directory.h
libstored/data/include/libstored/fifo.h
libstored/data/include/libstored/macros.h
libstored/data/include/libstored/pipes.h
libstored/data/include/libstored/poller.h
libstored/data/include/libstored/protocol.h
libstored-2.1.0.dist-info/licenses/LICENSE
libstored-2.1.0.dist-info/METADATA
libstored-2.1.0.dist-info/WHEEL
libstored-2.1.0.dist-info/entry_points.txt
libstored-2.1.0.dist-info/top_level.txt
libstored-2.1.0.dist-info/RECORD
