Metadata-Version: 2.4
Name: libstored
Version: 2.1.0
Summary: Python generator and tools for libstored
Home-page: https://github.com/DEMCON/libstored
Author: Jochem Rutgers
Author-email: jochem.rutgers@demcon.com
License: MPLv2.0
Classifier: Programming Language :: Python :: 3
Classifier: Programming Language :: C++
Classifier: Development Status :: 5 - Production/Stable
Classifier: Intended Audience :: Developers
Classifier: Topic :: Software Development :: Code Generators
Classifier: Topic :: Software Development :: Debuggers
Classifier: Topic :: Software Development :: Embedded Systems
Requires-Python: >=3.10
License-File: LICENSE
Requires-Dist: aiofiles
Requires-Dist: crcmod
Requires-Dist: filelock
Requires-Dist: jinja2
Requires-Dist: matplotlib
Requires-Dist: natsort
Requires-Dist: platformdirs
Requires-Dist: pycryptodome
Requires-Dist: pyserial>=3.1
Requires-Dist: pyzmq
Requires-Dist: textx
Requires-Dist: tornado>=6.1; platform_system == "Windows"
Dynamic: license-file
